{
  "vitalinfo": [
    {
      "patient_id": 1,
      "vitalinfo_id": 10,
      "allergies": "hcwbysmzpfseqyjrjhxa",
      "blood_type": "yfhhkdqiclsqgitsucjb",
      "drinker": "lqqyidwodgeegvosueiz",
      "family_hist": "gochpyzssgcrrlcayaji",
      "height": {
        "unit": "cm",
        "value": "qrqnjolowogdgdnpjmij"
      },
      "medical_conditions": "awztkjrnclqjwnlqqero",
      "overseas": {
        "destinations": "pstjcgpxdqovvurfukvx",
        "recently": "bojxfpbexjbmeixuevhu"
      },
      "smoker": "cwxberatacxhpwegzdfe",
      "weight": {
        "unit": "lb",
        "value": "hmdheiwwiiyyaoyqhgfu"
      }
    },
    {
      "patient_id": 1,
      "vitalinfo_id": 11,
      "allergies": "hcwbysmzpfseqyjrjhxa",
      "blood_type": "yfhhkdqiclsqgitsucjb",
      "drinker": "lqqyidwodgeegvosueiz",
      "family_hist": "gochpyzssgcrrlcayaji",
      "height": {
        "unit": "cm",
        "value": "qrqnjolowogdgdnpjmij"
      },
      "medical_conditions": "awztkjrnclqjwnlqqero",
      "overseas": {
        "destinations": "pstjcgpxdqovvurfukvx",
        "recently": "bojxfpbexjbmeixuevhu"
      },
      "smoker": "cwxberatacxhpwegzdfe",
      "weight": {
        "unit": "lb",
        "value": "hmdheiwwiiyyaoyqhgfu"
      }
    },
    {
      "patient_id": 2,
      "vitalinfo_id": 12,
      "allergies": "hcwbysmzpfseqyjrjhxa",
      "blood_type": "yfhhkdqiclsqgitsucjb",
      "drinker": "lqqyidwodgeegvosueiz",
      "family_hist": "gochpyzssgcrrlcayaji",
      "height": {
        "unit": "cm",
        "value": "qrqnjolowogdgdnpjmij"
      },
      "medical_conditions": "awztkjrnclqjwnlqqero",
      "overseas": {
        "destinations": "pstjcgpxdqovvurfukvx",
        "recently": "bojxfpbexjbmeixuevhu"
      },
      "smoker": "cwxberatacxhpwegzdfe",
      "weight": {
        "unit": "lb",
        "value": "hmdheiwwiiyyaoyqhgfu"
      }
    },
    {
      "patient_id": 3,
      "vitalinfo_id": 13,
      "allergies": "hcwbysmzpfseqyjrjhxa",
      "blood_type": "yfhhkdqiclsqgitsucjb",
      "drinker": "lqqyidwodgeegvosueiz",
      "family_hist": "gochpyzssgcrrlcayaji",
      "height": {
        "unit": "cm",
        "value": "qrqnjolowogdgdnpjmij"
      },
      "medical_conditions": "awztkjrnclqjwnlqqero",
      "overseas": {
        "destinations": "pstjcgpxdqovvurfukvx",
        "recently": "bojxfpbexjbmeixuevhu"
      },
      "smoker": "cwxberatacxhpwegzdfe",
      "weight": {
        "unit": "lb",
        "value": "hmdheiwwiiyyaoyqhgfu"
      }
    }
  ]
}